masterai_oss/__init__.py
masterai_oss/__version__.py
masterai_oss/models.py
masterai_oss/oss.py
masterai_oss/utils.py
masterai_oss-2023.8.1.dist-info/LICENSE
masterai_oss-2023.8.1.dist-info/METADATA
masterai_oss-2023.8.1.dist-info/WHEEL
masterai_oss-2023.8.1.dist-info/top_level.txt
masterai_oss-2023.8.1.dist-info/RECORD
