Metadata-Version: 2.1
Name: masterai-oss
Version: 2023.8.1
Summary: masterai oss
Author: zhazhazhui
Author-email: zhazhahui@masterai.com
License: MIT
Classifier: License :: OSI Approved :: MIT License
Classifier: Programming Language :: Python :: 3.6
Classifier: Programming Language :: Python :: 3.7
Classifier: Programming Language :: Python :: 3.8
Classifier: Programming Language :: Python :: Implementation :: CPython
Classifier: Programming Language :: Python :: Implementation :: PyPy
Requires-Python: >=3.6.0
License-File: LICENSE
Requires-Dist: boto3 >=1.26.76
Requires-Dist: botocore >=1.29.76
Requires-Dist: tenacity >=8.0.1
Requires-Dist: pydantic >=1.9.2
